DrillEda.py
DrillEda-0.1.4.dist-info/LICENSE
DrillEda-0.1.4.dist-info/METADATA
DrillEda-0.1.4.dist-info/WHEEL
DrillEda-0.1.4.dist-info/top_level.txt
DrillEda-0.1.4.dist-info/RECORD
