Metadata-Version: 2.1
Name: DrillEda
Version: 0.1.4
Summary: A package for exploratory data analysis of drillhole data.
Home-page: https://github.com/Mining-Geologist/drill_eda
Author: Mining Geologist
Author-email: geologytrainings@gmail.com
License: UNKNOWN
Platform: UNKNOWN
Classifier: Programming Language :: Python :: 3.9
Classifier: License :: OSI Approved :: MIT License
Classifier: Operating System :: OS Independent
Requires-Python: >=3.9
License-File: LICENSE
Requires-Dist: pandas==1.4.2
Requires-Dist: matplotlib==3.5.2
Requires-Dist: numpy==1.26.4
